gearyov_drf_error_formatter/__init__.py
gearyov_drf_error_formatter/exception_handler.py
gearyov_drf_error_formatter-0.1.3.dist-info/METADATA
gearyov_drf_error_formatter-0.1.3.dist-info/WHEEL
gearyov_drf_error_formatter-0.1.3.dist-info/RECORD
