Metadata-Version: 2.3
Name: gearyov-drf-error-formatter
Version: 0.1.3
Summary: Custom DRF exception handler that formats all exceptions into a consistent JSON payload
Author: Vladyslav Shesternyov
Author-email: vladyslav.shesternyov22@gmail.com
Requires-Python: >=3.12
Classifier: Programming Language :: Python :: 3
Classifier: Programming Language :: Python :: 3.12
Classifier: Programming Language :: Python :: 3.13
Requires-Dist: django (>=4.2,<6.0)
Requires-Dist: djangorestframework (>=3.14,<4.0)
